poetry_base/__init__.py
poetry_meu_pip-5.1.0.dist-info/METADATA
poetry_meu_pip-5.1.0.dist-info/WHEEL
poetry_meu_pip-5.1.0.dist-info/RECORD
