Metadata-Version: 2.1
Name: poetry-meu-pip
Version: 5.1.0
Summary: Projeto final da disciplina de gces - UnB
Author: ArthurMeloG
Requires-Python: >=3.9,<4.0
Classifier: Programming Language :: Python :: 3
Classifier: Programming Language :: Python :: 3.9
Classifier: Programming Language :: Python :: 3.10
Classifier: Programming Language :: Python :: 3.11
Requires-Dist: altair (==4.2.0)
